{
    "identityPoolName": "seventeenAuth",
    "allowUnauthenticatedIdentities": false,
    "thirdPartyAuth": false,
    "lambdaLogPolicy": "seventeenAuth_lambda_log_policy",
    "openIdLambdaRoleName": "seventeenAuth_openid_lambda_role",
    "openIdRolePolicy": "seventeenAuth_openid_pass_role_policy",
    "openIdLambdaIAMPolicy": "seventeenAuth_openid_lambda_iam_policy",
    "openIdLogPolicy": "seventeenAuth_openid_lambda_log_policy",
    "userPoolName": "seventeenAuth",
    "autoVerifiedAttributes": [
        "email"
    ],
    "mfaConfiguration": "OFF",
    "mfaTypes": [
        "SMS Text Message"
    ],
    "roleName": "seventeenAuth_sns-role",
    "roleExternalId": "seventeenAuth_role_external_id",
    "policyName": "seventeenAuth-sns-policy",
    "smsAuthenticationMessage": "Your authentication code is {####}",
    "smsVerificationMessage": "Your verification code is {####}",
    "emailVerificationSubject": "Your verification code",
    "emailVerificationMessage": "Your verification code is {####}",
    "defaultPasswordPolicy": true,
    "passwordPolicyMinLength": "6",
    "passwordPolicyCharacters": [],
    "requiredAttributes": [
        "email"
    ],
    "userpoolClientName": "seventeenAuth_app_client",
    "userpoolClientGenerateSecret": true,
    "userpoolClientRefreshTokenValidity": 30,
    "userpoolClientReadAttributes": [
        "email"
    ],
    "mfaLambdaRole": "seventeenAuth_totp_lambda_role",
    "mfaLambdaLogPolicy": "seventeenAuth_totp_lambda_log_policy",
    "mfaPassRolePolicy": "seventeenAuth_totp_pass_role_policy",
    "mfaLambdaIAMPolicy": "seventeenAuth_totp_lambda_iam_policy",
    "userpoolClientLambdaRole": "seventeenAuth_userpoolclient_lambda_role",
    "userpoolClientLogPolicy": "seventeenAuth_userpoolclient_lambda_log_policy",
    "userpoolClientLambdaPolicy": "seventeenAuth_userpoolclient_lambda_iam_policy",
    "userpoolClientSetAttributes": false,
    "useDefault": "manual",
    "authSelections": "identityPoolAndUserPool",
    "resourceName": "seventeenAuth",
    "authRoleName": {
        "Ref": "AuthRoleName"
    },
    "unauthRoleName": {
        "Ref": "UnauthRoleName"
    },
    "authRoleArn": {
        "Fn::GetAtt": [
            "AuthRole",
            "Arn"
        ]
    },
    "unauthRoleArn": {
        "Fn::GetAtt": [
            "UnauthRole",
            "Arn"
        ]
    }
}